{
  "transit" : {
    "dynamicSearchWindow" : {
      "minWindow" : "4h",
      "maxWindow" : "16h"
    }
  },
  "updaters": [
    /*{
      "type": "vehicle-parking",
      "feedId": "parking",
      "sourceType": "siri-fm",
      "url": "https://transmodel.api.opendatahub.com/siri-lite/fm/parking"
    },*/
    {
      "type": "siri-et-light",
      "feedId": "sta",
      "url": "https://efa.sta.bz.it/siri-lite/estimated-timetable/xml",
      "fuzzyTripMatching": true
    },
    {
      "type": "siri-sx-light",
      "feedId": "sta",
      "url": "https://efa.sta.bz.it/siri-lite/situation-exchange/xml"
    }
  ]
}
